{"cameraMode":{"drawMode":0,"name":"Shaded","section":"Shading Mode"},"sceneLighting":false,"audioPlay":false,"sceneViewState":{"m_AlwaysRefresh":false,"showFog":true,"showSkybox":false,"showFlares":true,"showImageEffects":true,"showParticleSystems":true,"showVisualEffectGraphs":true,"m_FxEnabled":true},"in2DMode":false,"pivot":{"x":0.0915566086769104,"y":-0.6311159133911133,"z":1.17134428024292},"rotation":{"x":-0.25781720876693728,"y":0.06255297362804413,"z":-0.016679732128977777,"w":-0.9640582203865051},"size":5.412435531616211,"orthographic":false}