{"cameraMode":{"drawMode":0,"name":"Shaded","section":"Shading Mode"},"sceneLighting":true,"audioPlay":false,"sceneViewState":{"m_AlwaysRefresh":false,"showFog":true,"showSkybox":true,"showFlares":true,"showImageEffects":true,"showParticleSystems":true,"showVisualEffectGraphs":true,"m_FxEnabled":true},"in2DMode":false,"pivot":{"x":16.8700008392334,"y":0.4300000071525574,"z":-15.610000610351563},"rotation":{"x":-0.41976913809776308,"y":-0.13371093571186067,"z":0.06269751489162445,"w":-0.895575225353241},"size":20.427141189575197,"orthographic":false}