{"cameraMode":{"drawMode":0,"name":"Shaded","section":"Shading Mode"},"sceneLighting":true,"audioPlay":false,"sceneViewState":{"m_AlwaysRefresh":false,"showFog":true,"showSkybox":true,"showFlares":true,"showImageEffects":true,"showParticleSystems":true,"showVisualEffectGraphs":true,"m_FxEnabled":true},"in2DMode":false,"pivot":{"x":3.2699995040893556,"y":4.0,"z":-34.099998474121097},"rotation":{"x":-0.019893214106559755,"y":-0.6844900846481323,"z":0.0187084823846817,"w":-0.7285631895065308},"size":11.22435474395752,"orthographic":false}